jsrun-0.1.0.dist-info/METADATA
jsrun-0.1.0.dist-info/WHEEL
jsrun-0.1.0.dist-info/licenses/LICENSE
jsrun/__init__.py
jsrun/__main__.py
jsrun/_jsrun.cpython-314t-aarch64-linux-gnu.so
jsrun/_jsrun.pyi
jsrun/py.typed
jsrun-0.1.0.dist-info/RECORD
