Metadata-Version: 2.4
Name: jsrun
Version: 0.1.0
Classifier: Typing :: Typed
Classifier: Intended Audience :: Developers
Classifier: License :: OSI Approved :: MIT License
Classifier: Programming Language :: Python :: 3
Classifier: Programming Language :: Python :: 3.10
Classifier: Programming Language :: Python :: 3.11
Classifier: Programming Language :: Python :: 3.12
Classifier: Programming Language :: Python :: 3.13
Classifier: Programming Language :: Python :: 3.14
Classifier: Programming Language :: Python :: Implementation :: CPython
Classifier: Programming Language :: Python :: Implementation :: PyPy
Classifier: Programming Language :: Rust
Classifier: Operating System :: MacOS
Classifier: Operating System :: POSIX :: Linux
Classifier: Topic :: Software Development :: Libraries :: Python Modules
License-File: LICENSE
Summary: Modern embedded JavaScript runtime for Python powered by V8 and Rust.
Keywords: javascript,v8,pyo3,asyncio,rust-extension
Author-email: Xin Fu <xin@imfing.com>
License-Expression: MIT
Requires-Python: >=3.10
Project-URL: Homepage, https://github.com/imfing/jsrun
Project-URL: Repository, https://github.com/imfing/jsrun
